[{"place_id": 252297674, "licence": "Data \u00a9 OpenStreetMap contributors, ODbL 1.0. http://osm.org/copyright", "osm_type": "node", "osm_id": 429918282, "lat": "12.9357366", "lon": "77.6240810", "class": "place", "type": "suburb", "place_rank": 19, "importance": 0.14673761120012202, "addresstype": "suburb", "name": "Koramangala", "display_name": "Koramangala, Sri Lakshmi Devi Ward, Bengaluru South City Corporation, Bengaluru, Bangalore South, Bengaluru Urban, Karnataka, 560095, India", "boundingbox": ["12.9157366", "12.9557366", "77.6040810", "77.6440810"]}]